AUTHORS.txt
LICENSE.txt
MANIFEST.in
README.rst
setup.py
jupyternotify/__init__.py
jupyternotify/jupyternotify.py
jupyternotify.egg-info/PKG-INFO
jupyternotify.egg-info/SOURCES.txt
jupyternotify.egg-info/dependency_links.txt
jupyternotify.egg-info/requires.txt
jupyternotify.egg-info/top_level.txt
jupyternotify/js/init.js
jupyternotify/js/notify.js