Metadata-Version: 1.1
Name: jupyternotify
Version: 0.1.15
Summary: A Jupyter Notebook %%magic for Browser Notifications of Cell Completion
Home-page: https://github.com/shoprunner/jupyter-notify
Author: Michelangelo D'Agostino
Author-email: mdagostino@shoprunner.com
License: BSD-3-Clause
Platform: UNKNOWN
Classifier: Programming Language :: Python :: 2.7
Classifier: Programming Language :: Python :: 3.6
